Workbook

Sheet STARBUCKS
A2: STARBUCKS CORPORATION - DCF MODEL WITH SCENARIO ANALYSIS
A6: Prepared By: Nitya Jignasu
A7: Date: 24/11//2025
H8: SCENARIO ANALYSIS SUMMARY
H9: Using a full DCF valuation framework with revenue growth, operating margin, WACC,
A10: COMPANY SNAPSHOT | H10: and terminal growth as key drivers, I evaluated Starbucks (SBUX) under Base, Bull, and Bear scenarios to understand valuation sensitivity.
A12: Headquarters: Seattle, Washington | H12: Base Case (Fair Value: $115)
A13: Industry: Coffee Retail | H13: Assumes moderate revenue growth, stable margins, and a 9% WACC.
A14: Ticker: SBUX | Exchange: NASDAQ | H14: This yields a valuation slightly above the current market pricing, indicating mild undervaluation.
A15: FY25 Revenue: $37.1 billion
A16: Market Cap: $90–100 billion range | H16: Bull Case (Fair Value: $157)
A17: Current Market Price: $83.34 | H17: Assumes stronger same-store growth, margin expansion, and an improved WACC due to reduced risk.
A18: Global Store Count: ~38,000+ | H18: This scenario implies meaningful upside if operating efficiency improves and macro conditions support higher consumer spending.
A19: Fiscal Year End: September 2025
H20: Bear Case (Fair Value: $89)
H21: Uses more conservative assumptions: lower revenue growth, margin pressure, and a higher cost of capital.
A22: Investment Thesis | H22: Reflects downside risk if inflation or weakening demand impacts profitability.
A24: Strong brand loyalty and global footprint supporting long-term revenue growth. | H24: Conclusion
A25: Margin recovery expected from operating efficiency initiatives. | H25: The valuation range ($89 – $157) highlights how sensitive Starbucks’ intrinsic value is to changes in growth and margins.
A26: International expansion (China, India) remains a major long-term growth driver. | H26: The Base Case suggests the stock is modestly undervalued, while the Bull Case indicates substantial upside potential if fundamentals strengthen.
A28: Key Risks
A30: Slowing consumer spending in core markets
A31: Commodity cost increases (coffee, dairy)
A32: FX volatility impacting international earnings
Q33: Prepared using publicly available data. For academic purpose only.

Sheet INPUT
A1: STARBUCKS HISTORICAL DATA
A2: Revenue | B2: 37184.4
A3: Revenue Growth % | B3: =VLOOKUP($B$22,$A$23:$E$26,2,FALSE) -> 0.04
A4: Operating Income | B4: 2936.6
A5: Operating Margin | B5: =VLOOKUP($B$22,$A$23:$E$26,3,FALSE) -> 0.08
A6: Net Income | B6: 1,856.4
A7: Depreciation and Amortization | B7: 1771.5
A8: Capex | B8: -2305.5
A9: Change in Working Capital | B9: -1494.4
A10: Interest Expense | B10: -542
A11: Income Taz Expense | B11: 650.6
A13: WACC | B13: =VLOOKUP($B$22,$A$23:$E$26,4,FALSE) -> 0.1
A14: Terminal Growth | B14: =VLOOKUP($B$22,$A$23:$E$26,5,FALSE) -> 0.02
A16: Cash | B16: 3219.8
A17: Short Term Debt | B17: 1498.9
A18: Long Term Debt | B18: 14575.9
A19: Net Debt | B19: 12855
A20: Shares Outstanding | B20: 1136.9
B22: Bear Case
A23: Scenario | B23: Revenue Growth | C23: Operating Margin | D23: WACC | E23: Terminal Growth
A24: Base Case | B24: 0.06 | C24: 0.1 | D24: 0.09 | E24: 0.025
A25: Bull Case | B25: 0.08 | C25: 0.12 | D25: 0.08 | E25: 0.03
A26: Bear Case | B26: 0.04 | C26: 0.08 | D26: 0.1 | E26: 0.02
A28: Reasoning:
B29: RG | C29: OM | D29: WACC | E29: TG
A30: Base Case | B30: long term CAGR | C30: Mid Range | D30: Starbucks WACC | E30: Long Term Growth
A31: Bull Case | B31: High End Growth | C31: Strong Margins | D31: Lower Risk | E31: Strong Expansion
A32: Bear Case | B32: Weak Macro | C32: Low Margins | D32: Higher Risk | E32: Slow Economy
K44: `

Sheet PROJECTIONS
B1: 2025A | C1: 2026E | D1: 2027E | E1: 2028E | F1: 2029E | G1: 2030E
A2: Revenue | B2: =INPUT!B2 -> 37184.4 | C2: =B2*(1+$B$3) -> 38671.776 | D2: =C2*(1+$B$3) -> 40218.647 | E2: =D2*(1+$B$3) -> 41827.393 | F2: =E2*(1+$B$3) -> 43500.489 | G2: =F2*(1+$B$3) -> 45240.508
A3: Revenue Growth % | B3: =INPUT!B3 -> 0.04 | C3: 0.06 | D3: 0.06 | E3: 0.06 | F3: 0.06 | G3: 0.06
A4: Operating Margin | B4: =INPUT!B5 -> 0.08 | C4: 0.1 | D4: 0.1 | E4: 0.1 | F4: 0.1 | G4: 0.1
A5: Operating Income | B5: =B2*B4 -> 2974.752 | C5: =C2*C4 -> 3867.1776 | D5: =D2*D4 -> 4021.8647 | E5: =E2*E4 -> 4182.7393 | F5: =F2*F4 -> 4350.0489 | G5: =G2*G4 -> 4524.0508
A6: Tax Rate | B6: 0.26 | C6: 0.26 | D6: 0.26 | E6: 0.26 | F6: 0.26 | G6: 0.26
A7: NOPAT | B7: =B5*(1-B6) -> 2201.3165 | C7: =C5*(1-C6) -> 2861.7114 | D7: =D5*(1-D6) -> 2976.1799 | E7: =E5*(1-E6) -> 3095.2271 | F7: =F5*(1-F6) -> 3219.0362 | G7: =G5*(1-G6) -> 3347.7976
A8: Depreciation & Amortization | B8: =INPUT!B7 -> 1771.5 | C8: =B8*(1+B3) -> 1842.36 | D8: =C8*(1+C3) -> 1952.9016 | E8: =D8*(1+D3) -> 2070.0757 | F8: =E8*(1+E3) -> 2194.2802 | G8: =F8*(1+F3) -> 2325.9371
A9: Capex | B9: =INPUT!B8 -> -2305.5 | C9: =B9*(1+B3) -> -2397.72 | D9: =C9*(1+C3) -> -2541.5832 | E9: =D9*(1+D3) -> -2694.0782 | F9: =E9*(1+E3) -> -2855.7229 | G9: =F9*(1+F3) -> -3027.0663
A10: Change in Working Capital | B10: =INPUT!B9 -> -1494.4 | C10: =B10*(1+B3) -> -1554.176 | D10: =C10*(1+C3) -> -1647.4266 | E10: =D10*(1+D3) -> -1746.2722 | F10: =E10*(1+E3) -> -1851.0485 | G10: =F10*(1+F3) -> -1962.1114
A11: Free Cash Flow | C11: =B7+B8-(B9)-(B10) -> 7772.7165 | D11: =C7+C8-(C9)-(C10) -> 8655.9674 | E11: =D7+D8-(D9)-(D10) -> 9118.0912 | F11: =E7+E8-(E9)-(E10) -> 9605.6531 | G11: =F7+F8-(F9)-(F10) -> 10120.088

Sheet DCF CALCULATION
A1: Year | B1: FCF | C1: WACC | D1: Dsicount Factor | E1: PV of FCF
A2: 2026E | B2: =PROJECTIONS!C11 -> 7772.7165 | C2: =INPUT!$B$13 -> 0.1 | D2: =1/(1+$C2)^1 -> 0.90909091 | E2: =B2*D2 -> 7066.1059
A3: 2027E | B3: =PROJECTIONS!D11 -> 8655.9674 | C3: =INPUT!$B$13 -> 0.1 | D3: =1/(1+$C3)^2 -> 0.82644628 | E3: =B3*D3 -> 7153.6921
A4: 2028E | B4: =PROJECTIONS!E11 -> 9118.0912 | C4: =INPUT!$B$13 -> 0.1 | D4: =1/(1+$C4)^3 -> 0.7513148 | E4: =B4*D4 -> 6850.5569
A5: 2029E | B5: =PROJECTIONS!F11 -> 9605.6531 | C5: =INPUT!$B$13 -> 0.1 | D5: =1/(1+$C5)^4 -> 0.68301346 | E5: =B5*D5 -> 6560.7903
A6: 2030E | B6: =PROJECTIONS!G11 -> 10120.088 | C6: =INPUT!$B$13 -> 0.1 | D6: =1/(1+$C6)^5 -> 0.62092132 | E6: =B6*D6 -> 6283.7783
A7: Sum of PV of FCF | E7: =SUM(E2:E6) -> 33914.923
A8: Terminal Value | B8: =B6*(1+INPUT!B14)/(INPUT!B13-INPUT!B14) -> 129031.12 | E8: =B8*D6 -> 80118.173
A9: Enterprise Value | E9: =E7+E8 -> 114033.1
A12: Equity Value | B12: =E9-INPUT!B19 -> 101178.1
A13: Fair Value per share | B13: =B12/INPUT!B20 -> 88.99472

Sheet SCENARIO OUTPUT
A3: Scenario | B3: Revenue Growth | C3: Operating Margin | D3: WACC | E3: Terminal Growth | F3: Fair Value per Share
A4: Base Case | B4: =VLOOKUP("Base Case",INPUT!A23:E26,2,FALSE) -> 0.06 | C4: =VLOOKUP("Base Case",INPUT!A23:E26,3,FALSE) -> 0.1 | D4: =VLOOKUP("Base Case",INPUT!A23:E26,4,FALSE) -> 0.09 | E4: =VLOOKUP("Base Case",INPUT!A23:E26,5,FALSE) -> 0.025 | F4: 115
A5: Bull Case | B5: =VLOOKUP("Bull Case",INPUT!A23:E26,2,FALSE) -> 0.08 | C5: =VLOOKUP("Bull Case",INPUT!A23:E26,3,FALSE) -> 0.12 | D5: =VLOOKUP("Bull Case",INPUT!A24:E27,4,FALSE) -> 0.08 | E5: =VLOOKUP("Bull Case",INPUT!A24:E27,5,FALSE) -> 0.03 | F5: 157
A6: Bear Case | B6: =VLOOKUP("Bear Case",INPUT!A23:E26,2,FALSE) -> 0.04 | C6: =VLOOKUP("Bear Case",INPUT!A23:E26,3,FALSE) -> 0.08 | D6: =VLOOKUP("Bear Case",INPUT!A25:E27,4,FALSE) -> 0.1 | E6: =VLOOKUP("Bear Case",INPUT!A25:E27,5,FALSE) -> 0.02 | F6: 89
